Workbook
Name Slicer_Hospital_Name: #N/A
Name Slicer_Month: #N/A

Sheet Dashboard
A1: CAREPLUS HEALTHCARE - EXECUTIVE OPERATIONS & PERFORMANCE DASHBOARD
A4: Total Revenue | C4: Total Appointments | E4: Average Wait Time | G4: Average Patient Rating
A5: =SUM(Appointment_Transactions[Appointment_Fee]) -> 671650 | C5: =COUNTA(Appointment_Transactions[Appointment_ID]) -> 808 | E5: =AVERAGE(Appointment_Transactions[Waiting_Time_Minutes]) -> 26.429455 | G5: =AVERAGE(Appointment_Transactions[Patient_Rating]) -> 3.9232614

Sheet Deep Dive
B2: Day of Week | C2: Appointment Count | E2: Insurance Status | F2: Count | H2: Payment Method | I2: Count | K2: Holiday Name | L2: Date | M2: Operation Status | N2: Appointment Volume
B3: Monday | C3: =COUNTIF(Appointment_Transactions[Weekday], B3) -> 119 | E3: Yes | F3: =COUNTIF(Appointments!U:U,"Yes") -> 326 | H3: {=_xlfn.UNIQUE(Appointment_Transactions[Payment_Mode])} -> UPI | I3: =COUNTIF(Appointment_Transactions[Payment_Mode],'Deep Dive'!H3) -> 466 | K3: {=_xlfn.UNIQUE(Holiday_Calendar[Holiday_Name])} -> New Year's Day | L3: =_xlfn.XLOOKUP('Deep Dive'!K3,Holiday_Calendar[Holiday_Name],Holiday_Calendar[Holiday_Date],,0) -> 45658 | M3: =_xlfn.XLOOKUP(K3,Holiday_Calendar[Holiday_Name],Holiday_Calendar[Hospital_Operation]) -> Emergency Only | N3: =COUNTIF(Appointment_Transactions[Appointment_Date],L3) -> 3
B4: Tuesday | C4: =COUNTIF(Appointment_Transactions[Weekday], B4) -> 123 | E4: No | F4: =COUNTIF(Appointments!U:U,"No") -> 482 | H4: Card | I4: =COUNTIF(Appointment_Transactions[Payment_Mode],'Deep Dive'!H4) -> 105 | K4: Pongal | L4: =_xlfn.XLOOKUP('Deep Dive'!K4,Holiday_Calendar[Holiday_Name],Holiday_Calendar[Holiday_Date],,0) -> 45671 | M4: =_xlfn.XLOOKUP(K4,Holiday_Calendar[Holiday_Name],Holiday_Calendar[Hospital_Operation]) -> Emergency Only | N4: =COUNTIF(Appointment_Transactions[Appointment_Date],L4) -> 8
B5: Wednesday | C5: =COUNTIF(Appointment_Transactions[Weekday], B5) -> 108 | H5: Cash | I5: =COUNTIF(Appointment_Transactions[Payment_Mode],'Deep Dive'!H5) -> 129 | K5: Republic Day | L5: =_xlfn.XLOOKUP('Deep Dive'!K5,Holiday_Calendar[Holiday_Name],Holiday_Calendar[Holiday_Date],,0) -> 45683 | M5: =_xlfn.XLOOKUP(K5,Holiday_Calendar[Holiday_Name],Holiday_Calendar[Hospital_Operation]) -> Emergency Only | N5: =COUNTIF(Appointment_Transactions[Appointment_Date],L5) -> 6
B6: Thursday | C6: =COUNTIF(Appointment_Transactions[Weekday], B6) -> 120 | H6: Insurance | I6: =COUNTIF(Appointment_Transactions[Payment_Mode],'Deep Dive'!H6) -> 108 | K6: Mahashivratri | L6: =_xlfn.XLOOKUP('Deep Dive'!K6,Holiday_Calendar[Holiday_Name],Holiday_Calendar[Holiday_Date],,0) -> 45714 | M6: =_xlfn.XLOOKUP(K6,Holiday_Calendar[Holiday_Name],Holiday_Calendar[Hospital_Operation]) -> Normal | N6: =COUNTIF(Appointment_Transactions[Appointment_Date],L6) -> 2
B7: Friday | C7: =COUNTIF(Appointment_Transactions[Weekday], B7) -> 114 | K7: Tamil New Year | L7: =_xlfn.XLOOKUP('Deep Dive'!K7,Holiday_Calendar[Holiday_Name],Holiday_Calendar[Holiday_Date],,0) -> 45761 | M7: =_xlfn.XLOOKUP(K7,Holiday_Calendar[Holiday_Name],Holiday_Calendar[Hospital_Operation]) -> Emergency Only | N7: =COUNTIF(Appointment_Transactions[Appointment_Date],L7) -> 5
B8: Saturday | C8: =COUNTIF(Appointment_Transactions[Weekday], B8) -> 97 | K8: Good Friday | L8: =_xlfn.XLOOKUP('Deep Dive'!K8,Holiday_Calendar[Holiday_Name],Holiday_Calendar[Holiday_Date],,0) -> 45765 | M8: =_xlfn.XLOOKUP(K8,Holiday_Calendar[Holiday_Name],Holiday_Calendar[Hospital_Operation]) -> Normal | N8: =COUNTIF(Appointment_Transactions[Appointment_Date],L8) -> 5
B9: Sunday | C9: =COUNTIF(Appointment_Transactions[Weekday], B9) -> 127 | K9: Labour Day | L9: =_xlfn.XLOOKUP('Deep Dive'!K9,Holiday_Calendar[Holiday_Name],Holiday_Calendar[Holiday_Date],,0) -> 45778 | M9: =_xlfn.XLOOKUP(K9,Holiday_Calendar[Holiday_Name],Holiday_Calendar[Hospital_Operation]) -> Emergency Only | N9: =COUNTIF(Appointment_Transactions[Appointment_Date],L9) -> 6
K10: Bakrid | L10: =_xlfn.XLOOKUP('Deep Dive'!K10,Holiday_Calendar[Holiday_Name],Holiday_Calendar[Holiday_Date],,0) -> 45815 | M10: =_xlfn.XLOOKUP(K10,Holiday_Calendar[Holiday_Name],Holiday_Calendar[Hospital_Operation]) -> Normal | N10: =COUNTIF(Appointment_Transactions[Appointment_Date],L10) -> 3
K11: Independence Day | L11: =_xlfn.XLOOKUP('Deep Dive'!K11,Holiday_Calendar[Holiday_Name],Holiday_Calendar[Holiday_Date],,0) -> 45884 | M11: =_xlfn.XLOOKUP(K11,Holiday_Calendar[Holiday_Name],Holiday_Calendar[Hospital_Operation]) -> Emergency Only | N11: =COUNTIF(Appointment_Transactions[Appointment_Date],L11) -> 0
K12: Gandhi Jayanti | L12: =_xlfn.XLOOKUP('Deep Dive'!K12,Holiday_Calendar[Holiday_Name],Holiday_Calendar[Holiday_Date],,0) -> 45932 | M12: =_xlfn.XLOOKUP(K12,Holiday_Calendar[Holiday_Name],Holiday_Calendar[Hospital_Operation]) -> Emergency Only | N12: =COUNTIF(Appointment_Transactions[Appointment_Date],L12) -> 0
K13: Deepavali | L13: =_xlfn.XLOOKUP('Deep Dive'!K13,Holiday_Calendar[Holiday_Name],Holiday_Calendar[Holiday_Date],,0) -> 45950 | M13: =_xlfn.XLOOKUP(K13,Holiday_Calendar[Holiday_Name],Holiday_Calendar[Hospital_Operation]) -> Emergency Only | N13: =COUNTIF(Appointment_Transactions[Appointment_Date],L13) -> 0
K14: Christmas | L14: =_xlfn.XLOOKUP('Deep Dive'!K14,Holiday_Calendar[Holiday_Name],Holiday_Calendar[Holiday_Date],,0) -> 46016 | M14: =_xlfn.XLOOKUP(K14,Holiday_Calendar[Holiday_Name],Holiday_Calendar[Hospital_Operation]) -> Emergency Only | N14: =COUNTIF(Appointment_Transactions[Appointment_Date],L14) -> 0

Sheet Operational_Analysis
A1: Department | B1: Count of Appointment_ID | D1: Doctor Name | E1: Count of Appointment_ID | G1: Count of Appointment_ID | H1: Column Labels
A2: Cardiology | B2: 77 | D2: Dr. Abinaya K | E2: 24 | G2: Department | H2: Cancelled | I2: Completed | J2: No Show | K2: Grand Total
A3: Dermatology | B3: 77 | D3: Dr. Ajith K | E3: 21 | G3: Cardiology | H3: 14 | I3: 53 | J3: 10 | K3: 77
A4: ENT | B4: 89 | D4: Dr. Anand S | E4: 16 | G4: Dermatology | H4: 11 | I4: 54 | J4: 12 | K4: 77
A5: General Medicine | B5: 89 | D5: Dr. Arun Kumar | E5: 13 | G5: ENT | H5: 17 | I5: 57 | J5: 15 | K5: 89
A6: Gynecology | B6: 83 | D6: Dr. Ashwin D | E6: 28 | G6: General Medicine | H6: 17 | I6: 51 | J6: 21 | K6: 89
A7: Neurology | B7: 89 | D7: Dr. Balaji V | E7: 19 | G7: Gynecology | H7: 12 | I7: 54 | J7: 17 | K7: 83
A8: Ophthalmology | B8: 72 | D8: Dr. Bharathi K | E8: 22 | G8: Neurology | H8: 16 | I8: 60 | J8: 13 | K8: 89
A9: Orthopedics | B9: 65 | D9: Dr. Deepa J | E9: 16 | G9: Ophthalmology | H9: 12 | I9: 52 | J9: 8 | K9: 72
A10: Pediatrics | B10: 82 | D10: Dr. Dinesh P | E10: 17 | G10: Orthopedics | H10: 18 | I10: 38 | J10: 9 | K10: 65
A11: Radiology | B11: 85 | D11: Dr. Divya R | E11: 25 | G11: Pediatrics | H11: 15 | I11: 54 | J11: 13 | K11: 82
A12: Grand Total | B12: 808 | D12: Dr. Gayathri R | E12: 16 | G12: Radiology | H12: 17 | I12: 53 | J12: 15 | K12: 85
D13: Dr. Gokul R | E13: 17 | G13: Grand Total | H13: 149 | I13: 526 | J13: 133 | K13: 808
D14: Dr. Hari Prasad | E14: 24
D15: Dr. Harini V | E15: 18
A16: Department | B16: Average of Waiting_Time_Minutes | D16: Dr. Jennifer A | E16: 25 | G16: Department | H16: Average of Consultation_Duration_Minutes
A17: Cardiology | B17: 51.311688 | D17: Dr. Karthik Raj | E17: 21 | G17: Cardiology | H17: 25
A18: Dermatology | B18: 24.571429 | D18: Dr. Kavitha M | E18: 14 | G18: Dermatology | H18: 15
A19: ENT | B19: 24.505618 | D19: Dr. Keerthana L | E19: 22 | G19: ENT | H19: 15
A20: General Medicine | B20: 23.078652 | D20: Dr. Lakshmi K | E20: 21 | G20: General Medicine | H20: 15
A21: Gynecology | B21: 25.192771 | D21: Dr. Mahesh R | E21: 18 | G21: Gynecology | H21: 15
A22: Neurology | B22: 23.707865 | D22: Dr. Manoj T | E22: 18 | G22: Neurology | H22: 30
A23: Ophthalmology | B23: 24.819444 | D23: Dr. Meena S | E23: 19 | G23: Ophthalmology | H23: 15
A24: Orthopedics | B24: 24.076923 | D24: Dr. Mohan V | E24: 23 | G24: Orthopedics | H24: 20
A25: Pediatrics | B25: 21.585366 | D25: Dr. Naveen C | E25: 22 | G25: Pediatrics | H25: 15
A26: Radiology | B26: 22.988235 | D26: Dr. Nisha T | E26: 15 | G26: Radiology | H26: 15
A27: Grand Total | B27: 26.429455 | D27: Dr. Prakash R | E27: 23 | G27: Grand Total | H27: 18.007426
D28: Dr. Priya Nair | E28: 18
D29: Dr. Ramesh G | E29: 20
D30: Dr. Ramya P | E30: 17
D31: Dr. Ranjani S | E31: 17
D32: Dr. Rekha N | E32: 23
D33: Dr. Sanjay P | E33: 15
D34: Dr. Saranya S | E34: 23
D35: Dr. Senthil M | E35: 17
D36: Dr. Siva Kumar | E36: 14
D37: Dr. Suresh B | E37: 20
D38: Dr. Swetha M | E38: 26
D39: Dr. Vignesh M | E39: 27
... D42: Grand Total | E42: 808

Sheet Patient_Hospital_Analysis
A1: Age | B1: Count of Appointment_ID | D1: Hospital | E1: Sum of Appointment_Fee | G1: Hospital | H1: Average of Patient_Rating
A2: 1 | B2: 12 | D2: CarePlus Coimbatore | E2: 79450 | G2: CarePlus Coimbatore | H2: 3.745098
A3: 2 | B3: 14 | D3: CarePlus Erode | E3: 91150 | G3: CarePlus Erode | H3: 3.9538462
A4: 3 | B4: 7 | D4: CarePlus Madurai | E4: 88500 | G4: CarePlus Madurai | H4: 4.0384615
A5: 4 | B5: 12 | D5: CarePlus Peelamedu | E5: 71450 | G5: CarePlus Peelamedu | H5: 3.8837209
A6: 5 | B6: 12 | D6: CarePlus Pollachi | E6: 72500 | G6: CarePlus Pollachi | H6: 3.8510638
A7: 6 | B7: 12 | D7: CarePlus Salem | E7: 93350 | G7: CarePlus Salem | H7: 4.0188679
A8: 7 | B8: 11 | D8: CarePlus Tiruppur | E8: 80200 | G8: CarePlus Tiruppur | H8: 3.9642857
A9: 8 | B9: 9 | D9: CarePlus Trichy | E9: 95050 | G9: CarePlus Trichy | H9: 3.9
A10: 9 | B10: 10 | D10: Grand Total | E10: 671650 | G10: Grand Total | H10: 3.9232614
A11: 10 | B11: 12
A12: 11 | B12: 10
A13: 12 | B13: 7
A14: 13 | B14: 5
A15: 14 | B15: 7
A16: 15 | B16: 14 | D16: Consultation Type | E16: Count of Appointment_ID
A17: 16 | B17: 11 | D17: Follow-up | E17: 280
A18: 17 | B18: 16 | D18: Online | E18: 289
A19: 18 | B19: 15 | D19: Walk-in | E19: 239
A20: 19 | B20: 12 | D20: Grand Total | E20: 808
A21: 20 | B21: 12
A22: 21 | B22: 4
A23: 22 | B23: 15
A24: 23 | B24: 9
A25: 24 | B25: 7
A26: 25 | B26: 5
A27: 26 | B27: 7
A28: 27 | B28: 7
A29: 28 | B29: 12
A30: 29 | B30: 3
A31: 30 | B31: 8
A32: 31 | B32: 15
... A86: 85 | B86: 9
A87: Grand Total | B87: 808

Sheet Hospitals
A1: Hospital_ID | B1: Hospital_Name | C1: City | D1: District | E1: Hospital_Type | F1: Hospital_Manager | G1: Opening_Date | H1: No_of_Doctors | I1: No_of_Beds | J1: ICU_Beds | K1: Emergency_Facility | L1: Parking | M1: Monthly_Patient_Target | N1: Monthly_Operational_Cost_INR | O1: Average_Occupancy_% | P1: Accreditation | Q1: Status
A2: H001 | B2: CarePlus Coimbatore | C2: Coimbatore | D2: Coimbatore | E2: Multi Speciality | F2: R. Karthikeyan | G2: 42106 | H2: 65 | I2: 250 | J2: 40 | K2: Yes | L2: Yes | M2: 12000 | N2: 12500000 | O2: 88 | P2: NABH | Q2: Active
A3: H002 | B3: CarePlus Peelamedu | C3: Coimbatore | D3: Coimbatore | E3: Multi Speciality | F3: P. Priya | G3: 42967 | H3: 48 | I3: 180 | J3: 28 | K3: Yes | L3: Yes | M3: 9000 | N3: 9200000 | O3: 84 | P3: NABH | Q3: Active
A4: H003 | B4: CarePlus Tiruppur | C4: Tiruppur | D4: Tiruppur | E4: Multi Speciality | F4: S. Prakash | G4: 43146 | H4: 52 | I4: 200 | J4: 30 | K4: Yes | L4: Yes | M4: 9800 | N4: 9800000 | O4: 86 | P4: NABH | Q4: Active
A5: H004 | B5: CarePlus Pollachi | C5: Pollachi | D5: Coimbatore | E5: General Hospital | F5: M. Ramesh | G5: 43626 | H5: 35 | I5: 140 | J5: 18 | K5: Yes | L5: Limited | M5: 6200 | N5: 6100000 | O5: 79 | P5: NABH Entry | Q5: Active
A6: H005 | B6: CarePlus Erode | C6: Erode | D6: Erode | E6: Multi Speciality | F6: L. Saranya | G6: 42692 | H6: 46 | I6: 175 | J6: 24 | K6: Yes | L6: Yes | M6: 8500 | N6: 8700000 | O6: 82 | P6: NABH | Q6: Active
A7: H006 | B7: CarePlus Salem | C7: Salem | D7: Salem | E7: Super Speciality | F7: V. Anand | G7: 41887 | H7: 72 | I7: 300 | J7: 50 | K7: Yes | L7: Yes | M7: 13500 | N7: 14800000 | O7: 91 | P7: NABH | Q7: Active
A8: H007 | B8: CarePlus Madurai | C8: Madurai | D8: Madurai | E8: Super Speciality | F8: K. Lakshmi | G8: 41609 | H8: 78 | I8: 320 | J8: 55 | K8: Yes | L8: Yes | M8: 14500 | N8: 16200000 | O8: 93 | P8: NABH | Q8: Active
A9: H008 | B9: CarePlus Trichy | C9: Tiruchirappalli | D9: Tiruchirappalli | E9: Multi Speciality | F9: A. Mohan | G9: 42816 | H9: 50 | I9: 210 | J9: 32 | K9: Yes | L9: Yes | M9: 10200 | N9: 10100000 | O9: 85 | P9: NABH | Q9: Active

Sheet Holidays
A1: Holiday_ID | B1: Holiday_Name | C1: Holiday_Date | D1: Day | E1: Holiday_Type | F1: Hospital_Operation | G1: Expected_Patient_Footfall | H1: Remarks
A2: HOL001 | B2: New Year's Day | C2: 45658 | D2: Wednesday | E2: National | F2: Emergency Only | G2: Low | H2: OP closed
A3: HOL002 | B3: Pongal | C3: 45671 | D3: Tuesday | E3: Festival | F3: Emergency Only | G3: Low | H3: Limited staff
A4: HOL003 | B4: Republic Day | C4: 45683 | D4: Sunday | E4: National | F4: Emergency Only | G4: Low | H4: Public holiday
A5: HOL004 | B5: Mahashivratri | C5: 45714 | D5: Wednesday | E5: Festival | F5: Normal | G5: Medium | H5: Regular OP
A6: HOL005 | B6: Tamil New Year | C6: 45761 | D6: Monday | E6: Festival | F6: Emergency Only | G6: Low | H6: Limited appointments
A7: HOL006 | B7: Good Friday | C7: 45765 | D7: Friday | E7: Religious | F7: Normal | G7: Medium | H7: Reduced appointments
A8: HOL007 | B8: Labour Day | C8: 45778 | D8: Thursday | E8: National | F8: Emergency Only | G8: Low | H8: Public holiday
A9: HOL008 | B9: Bakrid | C9: 45815 | D9: Saturday | E9: Religious | F9: Normal | G9: Medium | H9: Normal operations
A10: HOL009 | B10: Independence Day | C10: 45884 | D10: Friday | E10: National | F10: Emergency Only | G10: Low | H10: Public holiday
A11: HOL010 | B11: Gandhi Jayanti | C11: 45932 | D11: Thursday | E11: National | F11: Emergency Only | G11: Low | H11: Public holiday
A12: HOL011 | B12: Deepavali | C12: 45950 | D12: Monday | E12: Festival | F12: Emergency Only | G12: Very Low | H12: Limited staff
A13: HOL012 | B13: Christmas | C13: 46016 | D13: Thursday | E13: Religious | F13: Emergency Only | G13: Low | H13: Public holiday

Sheet Doctors
A1: Doctor_ID | B1: Doctor_Name | C1: Department | D1: Specialization | E1: Qualification | F1: Experience_Years | G1: Consultation_Fee_INR | H1: Hospital_ID | I1: Hospital_Name | J1: Availability | K1: Shift | L1: Avg_Consultation_Time_Min | M1: Daily_Capacity | N1: Status
A2: D001 | B2: Dr. Arun Kumar | C2: Cardiology | D2: Cardiologist | E2: MBBS, MD | F2: 5 | G2: 1200 | H2: H001 | I2: CarePlus Coimbatore | J2: Mon-Sat | K2: Morning | L2: 25 | M2: 19 | N2: Active
A3: D002 | B3: Dr. Priya Nair | C3: Orthopedics | D3: Orthopedic Surgeon | E3: MBBS, MD | F3: 7 | G3: 1000 | H3: H002 | I3: CarePlus Peelamedu | J3: Mon-Sat | K3: Evening | L3: 20 | M3: 24 | N3: Active
A4: D003 | B4: Dr. Karthik Raj | C4: General Medicine | D4: Physician | E4: MBBS, MD | F4: 9 | G4: 500 | H4: H003 | I4: CarePlus Tiruppur | J4: Mon-Sat | K4: Morning | L4: 15 | M4: 32 | N4: Active
A5: D004 | B5: Dr. Meena S | C5: Pediatrics | D5: Pediatrician | E5: MBBS, MD | F5: 11 | G5: 600 | H5: H004 | I5: CarePlus Pollachi | J5: Mon-Sat | K5: Evening | L5: 18 | M5: 26 | N5: Active
A6: D005 | B6: Dr. Hari Prasad | C6: Neurology | D6: Neurologist | E6: MBBS, MD | F6: 13 | G6: 1300 | H6: H005 | I6: CarePlus Erode | J6: Mon-Sat | K6: Morning | L6: 30 | M6: 16 | N6: Active
A7: D006 | B7: Dr. Divya R | C7: Dermatology | D7: Dermatologist | E7: MBBS, MD | F7: 15 | G7: 700 | H7: H006 | I7: CarePlus Salem | J7: Mon-Sat | K7: Evening | L7: 12 | M7: 40 | N7: Active
A8: D007 | B8: Dr. Mohan V | C8: Gynecology | D8: Gynecologist | E8: MBBS, MD | F8: 17 | G8: 900 | H8: H007 | I8: CarePlus Madurai | J8: Mon-Sat | K8: Morning | L8: 20 | M8: 24 | N8: Active
A9: D008 | B9: Dr. Lakshmi K | C9: ENT | D9: ENT Specialist | E9: MBBS, MD | F9: 19 | G9: 650 | H9: H008 | I9: CarePlus Trichy | J9: Mon-Sat | K9: Evening | L9: 15 | M9: 32 | N9: Active
A10: D009 | B10: Dr. Sanjay P | C10: Ophthalmology | D10: Ophthalmologist | E10: MBBS, MD | F10: 21 | G10: 700 | H10: H001 | I10: CarePlus Coimbatore | J10: Mon-Sat | K10: Morning | L10: 15 | M10: 32 | N10: Active
A11: D010 | B11: Dr. Nisha T | C11: Radiology | D11: Radiologist | E11: MBBS, MD | F11: 23 | G11: 800 | H11: H002 | I11: CarePlus Peelamedu | J11: Mon-Sat | K11: Evening | L11: 10 | M11: 48 | N11: Active
A12: D011 | B12: Dr. Ramesh G | C12: Cardiology | D12: Cardiologist | E12: MBBS, MD | F12: 3 | G12: 1200 | H12: H003 | I12: CarePlus Tiruppur | J12: Mon-Sat | K12: Morning | L12: 25 | M12: 19 | N12: Active
A13: D012 | B13: Dr. Kavitha M | C13: Orthopedics | D13: Orthopedic Surgeon | E13: MBBS, MD | F13: 5 | G13: 1000 | H13: H004 | I13: CarePlus Pollachi | J13: Mon-Sat | K13: Evening | L13: 20 | M13: 24 | N13: Active
... A41: D040 | B41: Dr. Balaji V | C41: Radiology | D41: Radiologist | E41: MBBS, MD | F41: 17 | G41: 800 | H41: H008 | I41: CarePlus Trichy | J41: Mon-Sat | K41: Evening | L41: 10 | M41: 48 | N41: Active

Sheet Departments
A1: Department_ID | B1: Department | C1: Head_of_Department | D1: No_of_Doctors | E1: Average_Consultation_Time_Min | F1: Daily_Patient_Capacity | G1: Average_Consultation_Fee_INR | H1: Priority_Level | I1: Common_Treatments | J1: Department_Status
A2: DEP001 | B2: Cardiology | C2: Dr. Arun Kumar | D2: 5 | E2: 25 | F2: 95 | G2: 1200 | H2: High | I2: Heart Disease, ECG, Hypertension | J2: Active
A3: DEP002 | B3: Orthopedics | C3: Dr. Priya Nair | D3: 4 | E3: 20 | F3: 110 | G3: 1000 | H3: High | I3: Fractures, Joint Pain | J3: Active
A4: DEP003 | B4: General Medicine | C4: Dr. Karthik Raj | D4: 8 | E4: 15 | F4: 220 | G4: 500 | H4: High | I4: Fever, Diabetes, BP | J4: Active
A5: DEP004 | B5: Pediatrics | C5: Dr. Meena S | D5: 4 | E5: 18 | F5: 120 | G5: 600 | H5: Medium | I5: Child Care, Vaccination | J5: Active
A6: DEP005 | B6: Neurology | C6: Dr. Hari Prasad | D6: 3 | E6: 30 | F6: 70 | G6: 1300 | H6: High | I6: Stroke, Migraine | J6: Active
A7: DEP006 | B7: Dermatology | C7: Dr. Divya R | D7: 3 | E7: 12 | F7: 150 | G7: 700 | H7: Low | I7: Skin & Hair Care | J7: Active
A8: DEP007 | B8: Gynecology | C8: Dr. Mohan V | D8: 4 | E8: 20 | F8: 105 | G8: 900 | H8: High | I8: Women's Health | J8: Active
A9: DEP008 | B9: ENT | C9: Dr. Lakshmi K | D9: 3 | E9: 15 | F9: 140 | G9: 650 | H9: Medium | I9: Ear, Nose & Throat | J9: Active
A10: DEP009 | B10: Ophthalmology | C10: Dr. Sanjay P | D10: 3 | E10: 15 | F10: 145 | G10: 700 | H10: Medium | I10: Eye Care | J10: Active
A11: DEP010 | B11: Radiology | C11: Dr. Nisha T | D11: 3 | E11: 10 | F11: 180 | G11: 800 | H11: Medium | I11: X-Ray, MRI, CT Scan | J11: Active

Sheet Appointments
A1: Appointment_ID | B1: Appointment_Date | C1: Appointment_Time | D1: Month | E1: Quarter | F1: Weekday | G1: Hospital_ID | H1: Hospital_Name | I1: Patient_ID | J1: Patient_Name | K1: Gender | L1: Age | M1: Department | N1: Doctor_ID | O1: Doctor_Name | P1: Consultation_Type | Q1: Appointment_Status | R1: Waiting_Time_Minutes | S1: Consultation_Duration_Minutes | T1: Appointment_Fee | U1: Insurance | V1: Payment_Mode | W1: Patient_Rating | X1: Follow_Up | Y1: Diagnosis_Category | Z1: Doctor_full_name
A2: APT00001 | B2: 45695 | C2: 0.57291667 | D2: Feb | E2: Q1 | F2: Friday | G2: H008 | H2: CarePlus Trichy | I2: PAT0146 | J2: Nisha | K2: Female | L2: 28 | M2: Ophthalmology | N2: D019 | O2: Dr 19 | P2: Follow-up | Q2: Completed | R2: 30 | S2: 15 | T2: 700 | U2: No | V2: UPI | W2: 4 | X2: No | Y2: Ophthalmology | Z2: =_xlfn.XLOOKUP(Appointment_Transactions[[#This Row],[Doctor_ID]],Doctor_Master[Doctor_ID],Doctor_Master[Doctor_Name],,0) -> Dr. Keerthana L
A3: APT00002 | B3: 45770 | C3: 0.58333333 | D3: Apr | E3: Q2 | F3: Wednesday | G3: H001 | H3: CarePlus Coimbatore | I3: PAT0175 | J3: Ravi | K3: Male | L3: 43 | M3: Orthopedics | N3: D002 | O3: Dr 2 | P3: Online | Q3: Completed | R3: 32 | S3: 20 | T3: 1000 | U3: No | V3: UPI | W3: 4 | X3: No | Y3: Orthopedics | Z3: =_xlfn.XLOOKUP(Appointment_Transactions[[#This Row],[Doctor_ID]],Doctor_Master[Doctor_ID],Doctor_Master[Doctor_Name],,0) -> Dr. Priya Nair
A4: APT00003 | B4: 45753 | C4: 0.8125 | D4: Apr | E4: Q2 | F4: Sunday | G4: H003 | H4: CarePlus Tiruppur | I4: PAT0395 | J4: Divya | K4: Female | L4: 79 | M4: General Medicine | N4: D023 | O4: Dr 23 | P4: Follow-up | Q4: Completed | R4: 24 | S4: 15 | T4: 500 | U4: No | V4: UPI | W4: 3 | X4: No | Y4: General Medicine | Z4: =_xlfn.XLOOKUP(Appointment_Transactions[[#This Row],[Doctor_ID]],Doctor_Master[Doctor_ID],Doctor_Master[Doctor_Name],,0) -> Dr. Gokul R
A5: APT00004 | B5: 45702 | C5: 0.45833333 | D5: Feb | E5: Q1 | F5: Friday | G5: H005 | H5: CarePlus Erode | I5: PAT0076 | J5: Lakshmi | K5: Male | L5: 28 | M5: Radiology | N5: D010 | O5: Dr 10 | P5: Online | Q5: Completed | R5: 27 | S5: 15 | T5: 800 | U5: No | V5: Card | W5: 4 | X5: Yes | Y5: Radiology | Z5: =_xlfn.XLOOKUP(Appointment_Transactions[[#This Row],[Doctor_ID]],Doctor_Master[Doctor_ID],Doctor_Master[Doctor_Name],,0) -> Dr. Nisha T
A6: APT00005 | B6: 45737 | C6: 0.48958333 | D6: Mar | E6: Q1 | F6: Friday | G6: H004 | H6: CarePlus Pollachi | I6: PAT0400 | J6: Lakshmi | K6: Female | L6: 41 | M6: Neurology | N6: D025 | O6: Dr 25 | P6: Online | Q6: Completed | R6: 20 | S6: 30 | T6: 1300 | U6: No | V6: UPI | W6: 5 | X6: No | Y6: Neurology | Z6: =_xlfn.XLOOKUP(Appointment_Transactions[[#This Row],[Doctor_ID]],Doctor_Master[Doctor_ID],Doctor_Master[Doctor_Name],,0) -> Dr. Bharathi K
A7: APT00006 | B7: 45811 | C7: 0.47916667 | D7: Jun | E7: Q2 | F7: Tuesday | G7: H006 | H7: CarePlus Salem | I7: PAT0313 | J7: Priya | K7: Male | L7: 8 | M7: Orthopedics | N7: D032 | O7: Dr 32 | P7: Online | Q7: Cancelled | R7: 31 | S7: 20 | T7: 1000 | U7: No | V7: Card | X7: No | Y7: Orthopedics | Z7: =_xlfn.XLOOKUP(Appointment_Transactions[[#This Row],[Doctor_ID]],Doctor_Master[Doctor_ID],Doctor_Master[Doctor_Name],,0) -> Dr. Gayathri R
A8: APT00007 | B8: 45693 | C8: 0.42708333 | D8: Feb | E8: Q1 | F8: Wednesday | G8: H006 | H8: CarePlus Salem | I8: PAT0281 | J8: Priya | K8: Male | L8: 7 | M8: Cardiology | N8: D001 | O8: Dr 1 | P8: Follow-up | Q8: Cancelled | R8: 66 | S8: 25 | T8: 1200 | U8: No | V8: UPI | X8: Yes | Y8: Cardiology | Z8: =_xlfn.XLOOKUP(Appointment_Transactions[[#This Row],[Doctor_ID]],Doctor_Master[Doctor_ID],Doctor_Master[Doctor_Name],,0) -> Dr. Arun Kumar
A9: APT00008 | B9: 45718 | C9: 0.55208333 | D9: Mar | E9: Q1 | F9: Sunday | G9: H001 | H9: CarePlus Coimbatore | I9: PAT0108 | J9: Mohan | K9: Female | L9: 76 | M9: General Medicine | N9: D033 | O9: Dr 33 | P9: Follow-up | Q9: Completed | R9: 11 | S9: 15 | T9: 500 | U9: No | V9: Cash | W9: 3 | X9: No | Y9: General Medicine | Z9: =_xlfn.XLOOKUP(Appointment_Transactions[[#This Row],[Doctor_ID]],Doctor_Master[Doctor_ID],Doctor_Master[Doctor_Name],,0) -> Dr. Vivek S
A10: APT00009 | B10: 45722 | C10: 0.78125 | D10: Mar | E10: Q1 | F10: Thursday | G10: H002 | H10: CarePlus Peelamedu | I10: PAT0064 | J10: Ravi | K10: Female | L10: 37 | M10: Orthopedics | N10: D012 | O10: Dr 12 | P10: Follow-up | Q10: Completed | R10: 46 | S10: 20 | T10: 1000 | U10: Yes | V10: Card | W10: 3 | X10: Yes | Y10: Orthopedics | Z10: =_xlfn.XLOOKUP(Appointment_Transactions[[#This Row],[Doctor_ID]],Doctor_Master[Doctor_ID],Doctor_Master[Doctor_Name],,0) -> Dr. Kavitha M
A11: APT00010 | B11: 45661 | C11: 0.46875 | D11: Jan | E11: Q1 | F11: Saturday | G11: H005 | H11: CarePlus Erode | I11: PAT0041 | J11: Arun | K11: Male | L11: 5 | M11: Dermatology | N11: D006 | O11: Dr 6 | P11: Online | Q11: Completed | R11: 11 | S11: 15 | T11: 700 | U11: Yes | V11: Insurance | X11: Yes | Y11: Dermatology | Z11: =_xlfn.XLOOKUP(Appointment_Transactions[[#This Row],[Doctor_ID]],Doctor_Master[Doctor_ID],Doctor_Master[Doctor_Name],,0) -> Dr. Divya R
A12: APT00011 | B12: 45835 | C12: 0.6875 | D12: Jun | E12: Q2 | F12: Friday | G12: H007 | H12: CarePlus Madurai | I12: PAT0084 | J12: Nisha | K12: Female | L12: 67 | M12: Gynecology | N12: D027 | O12: Dr 27 | P12: Walk-in | Q12: Completed | R12: 36 | S12: 15 | T12: 900 | U12: Yes | V12: Cash | X12: Yes | Y12: Gynecology | Z12: =_xlfn.XLOOKUP(Appointment_Transactions[[#This Row],[Doctor_ID]],Doctor_Master[Doctor_ID],Doctor_Master[Doctor_Name],,0) -> Dr. Siva Kumar
A13: APT00012 | B13: 45659 | C13: 0.51041667 | D13: Jan | E13: Q1 | F13: Thursday | G13: H007 | H13: CarePlus Madurai | I13: PAT0008 | J13: Kavin | K13: Male | L13: 3 | M13: Neurology | N13: D015 | O13: Dr 15 | P13: Follow-up | Q13: Cancelled | R13: 7 | S13: 30 | T13: 1300 | U13: No | V13: UPI | X13: Yes | Y13: Neurology | Z13: =_xlfn.XLOOKUP(Appointment_Transactions[[#This Row],[Doctor_ID]],Doctor_Master[Doctor_ID],Doctor_Master[Doctor_Name],,0) -> Dr. Vinoth K
A14: APT00013 | B14: 45819 | C14: 0.69791667 | D14: Jun | E14: Q2 | F14: Wednesday | G14: H007 | H14: CarePlus Madurai | I14: PAT0243 | J14: Mohan | K14: Male | L14: 83 | M14: Pediatrics | N14: D034 | O14: Dr 34 | P14: Follow-up | Q14: Completed | R14: 7 | S14: 15 | T14: 600 | U14: No | V14: UPI | W14: 3 | X14: Yes | Y14: Pediatrics | Z14: =_xlfn.XLOOKUP(Appointment_Transactions[[#This Row],[Doctor_ID]],Doctor_Master[Doctor_ID],Doctor_Master[Doctor_Name],,0) -> Dr. Abinaya K
A15: APT00014 | B15: 45797 | C15: 0.67708333 | D15: May | E15: Q2 | F15: Tuesday | G15: H007 | H15: CarePlus Madurai | I15: PAT0272 | J15: Meena | K15: Male | L15: 4 | M15: Orthopedics | N15: D032 | O15: Dr 32 | P15: Walk-in | Q15: Cancelled | R15: 30 | S15: 20 | T15: 1000 | U15: Yes | V15: UPI | X15: No | Y15: Orthopedics | Z15: =_xlfn.XLOOKUP(Appointment_Transactions[[#This Row],[Doctor_ID]],Doctor_Master[Doctor_ID],Doctor_Master[Doctor_Name],,0) -> Dr. Gayathri R
A16: APT00015 | B16: 45784 | C16: 0.66666667 | D16: May | E16: Q2 | F16: Wednesday | G16: H004 | H16: CarePlus Pollachi | I16: PAT0115 | J16: Priya | K16: Female | L16: 30 | M16: Neurology | N16: D015 | O16: Dr 15 | P16: Online | Q16: Completed | R16: 9 | S16: 30 | T16: 1300 | U16: Yes | V16: Insurance | X16: No | Y16: Neurology | Z16: =_xlfn.XLOOKUP(Appointment_Transactions[[#This Row],[Doctor_ID]],Doctor_Master[Doctor_ID],Doctor_Master[Doctor_Name],,0) -> Dr. Vinoth K
A17: APT00016 | B17: 45725 | C17: 0.84375 | D17: Mar | E17: Q1 | F17: Sunday | G17: H003 | H17: CarePlus Tiruppur | I17: PAT0260 | J17: Hari | K17: Female | L17: 16 | M17: Pediatrics | N17: D004 | O17: Dr 4 | P17: Online | Q17: Completed | R17: 27 | S17: 15 | T17: 600 | U17: Yes | V17: Cash | X17: Yes | Y17: Pediatrics | Z17: =_xlfn.XLOOKUP(Appointment_Transactions[[#This Row],[Doctor_ID]],Doctor_Master[Doctor_ID],Doctor_Master[Doctor_Name],,0) -> Dr. Meena S
A18: APT00017 | B18: 45738 | C18: 0.80208333 | D18: Mar | E18: Q1 | F18: Saturday | G18: H006 | H18: CarePlus Salem | I18: PAT0302 | J18: Meena | K18: Female | L18: 77 | M18: Ophthalmology | N18: D009 | O18: Dr 9 | P18: Follow-up | Q18: Completed | R18: 11 | S18: 15 | T18: 700 | U18: No | V18: UPI | W18: 4 | X18: No | Y18: Ophthalmology | Z18: =_xlfn.XLOOKUP(Appointment_Transactions[[#This Row],[Doctor_ID]],Doctor_Master[Doctor_ID],Doctor_Master[Doctor_Name],,0) -> Dr. Sanjay P
A19: APT00018 | B19: 45766 | C19: 0.47916667 | D19: Apr | E19: Q2 | F19: Saturday | G19: H008 | H19: CarePlus Trichy | I19: PAT0259 | J19: Nisha | K19: Male | L19: 33 | M19: Dermatology | N19: D026 | O19: Dr 26 | P19: Online | Q19: Completed | R19: 26 | S19: 15 | T19: 700 | U19: No | V19: UPI | W19: 4 | X19: Yes | Y19: Dermatology | Z19: =_xlfn.XLOOKUP(Appointment_Transactions[[#This Row],[Doctor_ID]],Doctor_Master[Doctor_ID],Doctor_Master[Doctor_Name],,0) -> Dr. Harini V
A20: APT00019 | B20: 45803 | C20: 0.45833333 | D20: May | E20: Q2 | F20: Monday | G20: H005 | H20: CarePlus Erode | I20: PAT0144 | J20: Mohan | K20: Male | L20: 39 | M20: Dermatology | N20: D036 | O20: Dr 36 | P20: Walk-in | Q20: Completed | R20: 5 | S20: 15 | T20: 700 | U20: No | V20: Card | W20: 3 | X20: Yes | Y20: Dermatology | Z20: =_xlfn.XLOOKUP(Appointment_Transactions[[#This Row],[Doctor_ID]],Doctor_Master[Doctor_ID],Doctor_Master[Doctor_Name],,0) -> Dr. Mahesh R
A21: APT00020 | B21: 45749 | C21: 0.85416667 | D21: Apr | E21: Q2 | F21: Wednesday | G21: H005 | H21: CarePlus Erode | I21: PAT0282 | J21: Meena | K21: Female | L21: 57 | M21: Ophthalmology | N21: D019 | O21: Dr 19 | P21: Online | Q21: Cancelled | R21: 18 | S21: 15 | T21: 700 | U21: No | V21: UPI | X21: Yes | Y21: Ophthalmology | Z21: =_xlfn.XLOOKUP(Appointment_Transactions[[#This Row],[Doctor_ID]],Doctor_Master[Doctor_ID],Doctor_Master[Doctor_Name],,0) -> Dr. Keerthana L
A22: APT00021 | B22: 45808 | C22: 0.33333333 | D22: May | E22: Q2 | F22: Saturday | G22: H003 | H22: CarePlus Tiruppur | I22: PAT0138 | J22: Lakshmi | K22: Female | L22: 76 | M22: Radiology | N22: D020 | O22: Dr 20 | P22: Follow-up | Q22: Completed | R22: 42 | S22: 15 | T22: 800 | U22: Yes | V22: UPI | W22: 5 | X22: Yes | Y22: Radiology | Z22: =_xlfn.XLOOKUP(Appointment_Transactions[[#This Row],[Doctor_ID]],Doctor_Master[Doctor_ID],Doctor_Master[Doctor_Name],,0) -> Dr. Ashwin D
A23: APT00022 | B23: 45727 | C23: 0.69791667 | D23: Mar | E23: Q1 | F23: Tuesday | G23: H005 | H23: CarePlus Erode | I23: PAT0048 | J23: Kavin | K23: Male | L23: 53 | M23: General Medicine | N23: D013 | O23: Dr 13 | P23: Walk-in | Q23: Completed | R23: 28 | S23: 15 | T23: 500 | U23: No | V23: UPI | W23: 4 | X23: Yes | Y23: General Medicine | Z23: =_xlfn.XLOOKUP(Appointment_Transactions[[#This Row],[Doctor_ID]],Doctor_Master[Doctor_ID],Doctor_Master[Doctor_Name],,0) -> Dr. Prakash R
A24: APT00023 | B24: 45691 | C24: 0.5 | D24: Feb | E24: Q1 | F24: Monday | G24: H003 | H24: CarePlus Tiruppur | I24: PAT0011 | J24: Divya | K24: Male | L24: 13 | M24: Gynecology | N24: D027 | O24: Dr 27 | P24: Follow-up | Q24: Completed | R24: 10 | S24: 15 | T24: 900 | U24: No | V24: UPI | W24: 4 | X24: Yes | Y24: Gynecology | Z24: =_xlfn.XLOOKUP(Appointment_Transactions[[#This Row],[Doctor_ID]],Doctor_Master[Doctor_ID],Doctor_Master[Doctor_Name],,0) -> Dr. Siva Kumar
A25: APT00024 | B25: 45776 | C25: 0.57291667 | D25: Apr | E25: Q2 | F25: Tuesday | G25: H003 | H25: CarePlus Tiruppur | I25: PAT0379 | J25: Mohan | K25: Female | L25: 48 | M25: Radiology | N25: D020 | O25: Dr 20 | P25: Walk-in | Q25: Completed | R25: 14 | S25: 15 | T25: 800 | U25: No | V25: Card | W25: 4 | X25: Yes | Y25: Radiology | Z25: =_xlfn.XLOOKUP(Appointment_Transactions[[#This Row],[Doctor_ID]],Doctor_Master[Doctor_ID],Doctor_Master[Doctor_Name],,0) -> Dr. Ashwin D
A26: APT00025 | B26: 45798 | C26: 0.35416667 | D26: May | E26: Q2 | F26: Wednesday | G26: H005 | H26: CarePlus Erode | I26: PAT0020 | J26: Arun | K26: Male | L26: 52 | M26: Gynecology | N26: D017 | O26: Dr 17 | P26: Follow-up | Q26: Completed | R26: 18 | S26: 15 | T26: 900 | U26: No | V26: Card | W26: 4 | X26: Yes | Y26: Gynecology | Z26: =_xlfn.XLOOKUP(Appointment_Transactions[[#This Row],[Doctor_ID]],Doctor_Master[Doctor_ID],Doctor_Master[Doctor_Name],,0) -> Dr. Suresh B
A27: APT00026 | B27: 45672 | C27: 0.45833333 | D27: Jan | E27: Q1 | F27: Wednesday | G27: H005 | H27: CarePlus Erode | I27: PAT0387 | J27: Hari | K27: Female | L27: 11 | M27: Gynecology | N27: D037 | O27: Dr 37 | P27: Follow-up | Q27: Completed | R27: 25 | S27: 15 | T27: 900 | U27: No | V27: Cash | W27: 4 | X27: Yes | Y27: Gynecology | Z27: =_xlfn.XLOOKUP(Appointment_Transactions[[#This Row],[Doctor_ID]],Doctor_Master[Doctor_ID],Doctor_Master[Doctor_Name],,0) -> Dr. Swetha M
A28: APT00027 | B28: 45764 | C28: 0.41666667 | D28: Apr | E28: Q2 | F28: Thursday | G28: H006 | H28: CarePlus Salem | I28: PAT0151 | J28: Meena | K28: Male | L28: 46 | M28: ENT | N28: D008 | O28: Dr 8 | P28: Walk-in | Q28: Completed | R28: 28 | S28: 15 | T28: 650 | U28: Yes | V28: UPI | X28: No | Y28: ENT | Z28: =_xlfn.XLOOKUP(Appointment_Transactions[[#This Row],[Doctor_ID]],Doctor_Master[Doctor_ID],Doctor_Master[Doctor_Name],,0) -> Dr. Lakshmi K
A29: APT00028 | B29: 45825 | C29: 0.8125 | D29: Jun | E29: Q2 | F29: Tuesday | G29: H003 | H29: CarePlus Tiruppur | I29: PAT0081 | J29: Hari | K29: Female | L29: 6 | M29: Ophthalmology | N29: D039 | O29: Dr 39 | P29: Follow-up | Q29: Completed | R29: 23 | S29: 15 | T29: 700 | U29: No | V29: Card | W29: 3 | X29: Yes | Y29: Ophthalmology | Z29: =_xlfn.XLOOKUP(Appointment_Transactions[[#This Row],[Doctor_ID]],Doctor_Master[Doctor_ID],Doctor_Master[Doctor_Name],,0) -> Dr. Ranjani S
A30: APT00029 | B30: 45766 | C30: 0.65625 | D30: Apr | E30: Q2 | F30: Saturday | G30: H002 | H30: CarePlus Peelamedu | I30: PAT0084 | J30: Divya | K30: Female | L30: 48 | M30: ENT | N30: D008 | O30: Dr 8 | P30: Online | Q30: Cancelled | R30: 5 | S30: 15 | T30: 650 | U30: No | V30: UPI | X30: No | Y30: ENT | Z30: =_xlfn.XLOOKUP(Appointment_Transactions[[#This Row],[Doctor_ID]],Doctor_Master[Doctor_ID],Doctor_Master[Doctor_Name],,0) -> Dr. Lakshmi K
A31: APT00030 | B31: 45798 | C31: 0.85416667 | D31: May | E31: Q2 | F31: Wednesday | G31: H007 | H31: CarePlus Madurai | I31: PAT0304 | J31: Meena | K31: Female | L31: 32 | M31: Gynecology | N31: D007 | O31: Dr 7 | P31: Walk-in | Q31: Cancelled | R31: 34 | S31: 15 | T31: 900 | U31: No | V31: Card | X31: Yes | Y31: Gynecology | Z31: =_xlfn.XLOOKUP(Appointment_Transactions[[#This Row],[Doctor_ID]],Doctor_Master[Doctor_ID],Doctor_Master[Doctor_Name],,0) -> Dr. Mohan V
A32: APT00031 | B32: 45737 | C32: 0.36458333 | D32: Mar | E32: Q1 | F32: Friday | G32: H008 | H32: CarePlus Trichy | I32: PAT0110 | J32: Meena | K32: Female | L32: 44 | M32: Neurology | N32: D035 | O32: Dr 35 | P32: Follow-up | Q32: Completed | R32: 21 | S32: 30 | T32: 1300 | U32: Yes | V32: Cash | X32: Yes | Y32: Neurology | Z32: =_xlfn.XLOOKUP(Appointment_Transactions[[#This Row],[Doctor_ID]],Doctor_Master[Doctor_ID],Doctor_Master[Doctor_Name],,0) -> Dr. Dinesh P
A33: APT00032 | B33: 45721 | C33: 0.80208333 | D33: Mar | E33: Q1 | F33: Wednesday | G33: H007 | H33: CarePlus Madurai | I33: PAT0194 | J33: Hari | K33: Male | L33: 37 | M33: Dermatology | N33: D006 | O33: Dr 6 | P33: Online | Q33: Completed | R33: 17 | S33: 15 | T33: 700 | U33: Yes | V33: UPI | W33: 4 | X33: No | Y33: Dermatology | Z33: =_xlfn.XLOOKUP(Appointment_Transactions[[#This Row],[Doctor_ID]],Doctor_Master[Doctor_ID],Doctor_Master[Doctor_Name],,0) -> Dr. Divya R
A34: APT00033 | B34: 45662 | C34: 0.4375 | D34: Jan | E34: Q1 | F34: Sunday | G34: H006 | H34: CarePlus Salem | I34: PAT0373 | J34: Kavin | K34: Female | L34: 84 | M34: General Medicine | N34: D013 | O34: Dr 13 | P34: Follow-up | Q34: No Show | R34: 29 | S34: 15 | T34: 500 | U34: Yes | V34: UPI | X34: Yes | Y34: General Medicine | Z34: =_xlfn.XLOOKUP(Appointment_Transactions[[#This Row],[Doctor_ID]],Doctor_Master[Doctor_ID],Doctor_Master[Doctor_Name],,0) -> Dr. Prakash R
A35: APT00034 | B35: 45720 | C35: 0.41666667 | D35: Mar | E35: Q1 | F35: Tuesday | G35: H007 | H35: CarePlus Madurai | I35: PAT0365 | J35: Hari | K35: Male | L35: 48 | M35: Dermatology | N35: D036 | O35: Dr 36 | P35: Online | Q35: Cancelled | R35: 29 | S35: 15 | T35: 700 | U35: No | V35: Cash | X35: Yes | Y35: Dermatology | Z35: =_xlfn.XLOOKUP(Appointment_Transactions[[#This Row],[Doctor_ID]],Doctor_Master[Doctor_ID],Doctor_Master[Doctor_Name],,0) -> Dr. Mahesh R
A36: APT00035 | B36: 45693 | C36: 0.80208333 | D36: Feb | E36: Q1 | F36: Wednesday | G36: H008 | H36: CarePlus Trichy | I36: PAT0206 | J36: Ravi | K36: Female | L36: 18 | M36: Radiology | N36: D040 | O36: Dr 40 | P36: Walk-in | Q36: Completed | R36: 39 | S36: 15 | T36: 800 | U36: Yes | V36: Card | W36: 3 | X36: No | Y36: Radiology | Z36: =_xlfn.XLOOKUP(Appointment_Transactions[[#This Row],[Doctor_ID]],Doctor_Master[Doctor_ID],Doctor_Master[Doctor_Name],,0) -> Dr. Balaji V
A37: APT00036 | B37: 45783 | C37: 0.44791667 | D37: May | E37: Q2 | F37: Tuesday | G37: H008 | H37: CarePlus Trichy | I37: PAT0138 | J37: Ravi | K37: Male | L37: 47 | M37: Orthopedics | N37: D022 | O37: Dr 22 | P37: Follow-up | Q37: No Show | R37: 26 | S37: 20 | T37: 1000 | U37: No | V37: UPI | X37: No | Y37: Orthopedics | Z37: =_xlfn.XLOOKUP(Appointment_Transactions[[#This Row],[Doctor_ID]],Doctor_Master[Doctor_ID],Doctor_Master[Doctor_Name],,0) -> Dr. Ramya P
A38: APT00037 | B38: 45683 | C38: 0.72916667 | D38: Jan | E38: Q1 | F38: Sunday | G38: H005 | H38: CarePlus Erode | I38: PAT0300 | J38: Nisha | K38: Male | L38: 49 | M38: Cardiology | N38: D021 | O38: Dr 21 | P38: Follow-up | Q38: Cancelled | R38: 36 | S38: 25 | T38: 1200 | U38: Yes | V38: Insurance | X38: No | Y38: Cardiology | Z38: =_xlfn.XLOOKUP(Appointment_Transactions[[#This Row],[Doctor_ID]],Doctor_Master[Doctor_ID],Doctor_Master[Doctor_Name],,0) -> Dr. Vignesh M
A39: APT00038 | B39: 45699 | C39: 0.35416667 | D39: Feb | E39: Q1 | F39: Tuesday | G39: H007 | H39: CarePlus Madurai | I39: PAT0138 | J39: Nisha | K39: Female | L39: 18 | M39: General Medicine | N39: D033 | O39: Dr 33 | P39: Online | Q39: No Show | R39: 31 | S39: 15 | T39: 500 | U39: No | V39: UPI | X39: No | Y39: General Medicine | Z39: =_xlfn.XLOOKUP(Appointment_Transactions[[#This Row],[Doctor_ID]],Doctor_Master[Doctor_ID],Doctor_Master[Doctor_Name],,0) -> Dr. Vivek S
A40: APT00039 | B40: 45801 | C40: 0.41666667 | D40: May | E40: Q2 | F40: Saturday | G40: H001 | H40: CarePlus Coimbatore | I40: PAT0222 | J40: Arun | K40: Female | L40: 63 | M40: Neurology | N40: D035 | O40: Dr 35 | P40: Follow-up | Q40: No Show | R40: 6 | S40: 30 | T40: 1300 | U40: No | V40: UPI | X40: No | Y40: Neurology | Z40: =_xlfn.XLOOKUP(Appointment_Transactions[[#This Row],[Doctor_ID]],Doctor_Master[Doctor_ID],Doctor_Master[Doctor_Name],,0) -> Dr. Dinesh P
A41: APT00040 | B41: 45800 | C41: 0.5 | D41: May | E41: Q2 | F41: Friday | G41: H001 | H41: CarePlus Coimbatore | I41: PAT0013 | J41: Priya | K41: Male | L41: 53 | M41: Pediatrics | N41: D024 | O41: Dr 24 | P41: Online | Q41: Completed | R41: 21 | S41: 15 | T41: 600 | U41: Yes | V41: Insurance | W41: 4 | X41: Yes | Y41: Pediatrics | Z41: =_xlfn.XLOOKUP(Appointment_Transactions[[#This Row],[Doctor_ID]],Doctor_Master[Doctor_ID],Doctor_Master[Doctor_Name],,0) -> Dr. Anand S
A42: APT00041 | B42: 45800 | C42: 0.33333333 | D42: May | E42: Q2 | F42: Friday | G42: H004 | H42: CarePlus Pollachi | I42: PAT0264 | J42: Hari | K42: Female | L42: 9 | M42: Neurology | N42: D035 | O42: Dr 35 | P42: Walk-in | Q42: Completed | R42: 32 | S42: 30 | T42: 1300 | U42: No | V42: Cash | X42: No | Y42: Neurology | Z42: =_xlfn.XLOOKUP(Appointment_Transactions[[#This Row],[Doctor_ID]],Doctor_Master[Doctor_ID],Doctor_Master[Doctor_Name],,0) -> Dr. Dinesh P
A43: APT00042 | B43: 45699 | C43: 0.60416667 | D43: Feb | E43: Q1 | F43: Tuesday | G43: H003 | H43: CarePlus Tiruppur | I43: PAT0151 | J43: Meena | K43: Female | L43: 4 | M43: Dermatology | N43: D016 | O43: Dr 16 | P43: Follow-up | Q43: Completed | R43: 40 | S43: 15 | T43: 700 | U43: Yes | V43: UPI | W43: 5 | X43: Yes | Y43: Dermatology | Z43: =_xlfn.XLOOKUP(Appointment_Transactions[[#This Row],[Doctor_ID]],Doctor_Master[Doctor_ID],Doctor_Master[Doctor_Name],,0) -> Dr. Deepa J
A44: APT00043 | B44: 45798 | C44: 0.36458333 | D44: May | E44: Q2 | F44: Wednesday | G44: H008 | H44: CarePlus Trichy | I44: PAT0201 | J44: Arun | K44: Male | L44: 25 | M44: Orthopedics | N44: D002 | O44: Dr 2 | P44: Follow-up | Q44: Completed | R44: 34 | S44: 20 | T44: 1000 | U44: No | V44: UPI | W44: 4 | X44: Yes | Y44: Orthopedics | Z44: =_xlfn.XLOOKUP(Appointment_Transactions[[#This Row],[Doctor_ID]],Doctor_Master[Doctor_ID],Doctor_Master[Doctor_Name],,0) -> Dr. Priya Nair
A45: APT00044 | B45: 45796 | C45: 0.33333333 | D45: May | E45: Q2 | F45: Monday | G45: H008 | H45: CarePlus Trichy | I45: PAT0113 | J45: Priya | K45: Male | L45: 77 | M45: ENT | N45: D028 | O45: Dr 28 | P45: Walk-in | Q45: Completed | R45: 38 | S45: 15 | T45: 650 | U45: Yes | V45: UPI | X45: Yes | Y45: ENT | Z45: =_xlfn.XLOOKUP(Appointment_Transactions[[#This Row],[Doctor_ID]],Doctor_Master[Doctor_ID],Doctor_Master[Doctor_Name],,0) -> Dr. Jennifer A
A46: APT00045 | B46: 45673 | C46: 0.67708333 | D46: Jan | E46: Q1 | F46: Thursday | G46: H006 | H46: CarePlus Salem | I46: PAT0324 | J46: Lakshmi | K46: Female | L46: 75 | M46: General Medicine | N46: D013 | O46: Dr 13 | P46: Online | Q46: Cancelled | R46: 26 | S46: 15 | T46: 500 | U46: No | V46: UPI | X46: Yes | Y46: General Medicine | Z46: =_xlfn.XLOOKUP(Appointment_Transactions[[#This Row],[Doctor_ID]],Doctor_Master[Doctor_ID],Doctor_Master[Doctor_Name],,0) -> Dr. Prakash R
A47: APT00046 | B47: 45727 | C47: 0.36458333 | D47: Mar | E47: Q1 | F47: Tuesday | G47: H006 | H47: CarePlus Salem | I47: PAT0192 | J47: Lakshmi | K47: Female | L47: 41 | M47: General Medicine | N47: D023 | O47: Dr 23 | P47: Follow-up | Q47: Completed | R47: 44 | S47: 15 | T47: 500 | U47: Yes | V47: UPI | W47: 3 | X47: Yes | Y47: General Medicine | Z47: =_xlfn.XLOOKUP(Appointment_Transactions[[#This Row],[Doctor_ID]],Doctor_Master[Doctor_ID],Doctor_Master[Doctor_Name],,0) -> Dr. Gokul R
A48: APT00047 | B48: 45821 | C48: 0.6875 | D48: Jun | E48: Q2 | F48: Friday | G48: H003 | H48: CarePlus Tiruppur | I48: PAT0387 | J48: Meena | K48: Male | L48: 60 | M48: ENT | N48: D018 | O48: Dr 18 | P48: Walk-in | Q48: Cancelled | R48: 24 | S48: 15 | T48: 650 | U48: No | V48: Card | X48: No | Y48: ENT | Z48: =_xlfn.XLOOKUP(Appointment_Transactions[[#This Row],[Doctor_ID]],Doctor_Master[Doctor_ID],Doctor_Master[Doctor_Name],,0) -> Dr. Naveen C
A49: APT00048 | B49: 45761 | C49: 0.77083333 | D49: Apr | E49: Q2 | F49: Monday | G49: H007 | H49: CarePlus Madurai | I49: PAT0186 | J49: Ravi | K49: Male | L49: 9 | M49: ENT | N49: D028 | O49: Dr 28 | P49: Walk-in | Q49: Completed | R49: 26 | S49: 15 | T49: 650 | U49: No | V49: UPI | W49: 3 | X49: Yes | Y49: ENT | Z49: =_xlfn.XLOOKUP(Appointment_Transactions[[#This Row],[Doctor_ID]],Doctor_Master[Doctor_ID],Doctor_Master[Doctor_Name],,0) -> Dr. Jennifer A
A50: APT00049 | B50: 45791 | C50: 0.77083333 | D50: May | E50: Q2 | F50: Wednesday | G50: H007 | H50: CarePlus Madurai | I50: PAT0168 | J50: Mohan | K50: Female | L50: 22 | M50: Radiology | N50: D040 | O50: Dr 40 | P50: Follow-up | Q50: Completed | R50: 17 | S50: 15 | T50: 800 | U50: Yes | V50: Insurance | W50: 3 | X50: No | Y50: Radiology | Z50: =_xlfn.XLOOKUP(Appointment_Transactions[[#This Row],[Doctor_ID]],Doctor_Master[Doctor_ID],Doctor_Master[Doctor_Name],,0) -> Dr. Balaji V
A51: APT00050 | B51: 45717 | C51: 0.63541667 | D51: Mar | E51: Q1 | F51: Saturday | G51: H003 | H51: CarePlus Tiruppur | I51: PAT0184 | J51: Hari | K51: Male | L51: 66 | M51: Pediatrics | N51: D004 | O51: Dr 4 | P51: Follow-up | Q51: Completed | R51: 6 | S51: 15 | T51: 600 | U51: No | V51: Cash | X51: No | Y51: Pediatrics | Z51: =_xlfn.XLOOKUP(Appointment_Transactions[[#This Row],[Doctor_ID]],Doctor_Master[Doctor_ID],Doctor_Master[Doctor_Name],,0) -> Dr. Meena S
A52: APT00051 | B52: 45664 | C52: 0.71875 | D52: Jan | E52: Q1 | F52: Tuesday | G52: H008 | H52: CarePlus Trichy | I52: PAT0160 | J52: Lakshmi | K52: Female | L52: 46 | M52: Dermatology | N52: D016 | O52: Dr 16 | P52: Online | Q52: Completed | R52: 11 | S52: 15 | T52: 700 | U52: No | V52: UPI | W52: 3 | X52: Yes | Y52: Dermatology | Z52: =_xlfn.XLOOKUP(Appointment_Transactions[[#This Row],[Doctor_ID]],Doctor_Master[Doctor_ID],Doctor_Master[Doctor_Name],,0) -> Dr. Deepa J
A53: APT00052 | B53: 45678 | C53: 0.83333333 | D53: Jan | E53: Q1 | F53: Tuesday | G53: H005 | H53: CarePlus Erode | I53: PAT0052 | J53: Arun | K53: Male | L53: 31 | M53: General Medicine | N53: D013 | O53: Dr 13 | P53: Online | Q53: No Show | R53: 30 | S53: 15 | T53: 500 | U53: No | V53: UPI | X53: No | Y53: General Medicine | Z53: =_xlfn.XLOOKUP(Appointment_Transactions[[#This Row],[Doctor_ID]],Doctor_Master[Doctor_ID],Doctor_Master[Doctor_Name],,0) -> Dr. Prakash R
A54: APT00053 | B54: 45730 | C54: 0.40625 | D54: Mar | E54: Q1 | F54: Friday | G54: H005 | H54: CarePlus Erode | I54: PAT0209 | J54: Arun | K54: Male | L54: 54 | M54: General Medicine | N54: D013 | O54: Dr 13 | P54: Online | Q54: Completed | R54: 24 | S54: 15 | T54: 500 | U54: No | V54: Card | W54: 5 | X54: Yes | Y54: General Medicine | Z54: =_xlfn.XLOOKUP(Appointment_Transactions[[#This Row],[Doctor_ID]],Doctor_Master[Doctor_ID],Doctor_Master[Doctor_Name],,0) -> Dr. Prakash R
A55: APT00054 | B55: 45741 | C55: 0.84375 | D55: Mar | E55: Q1 | F55: Tuesday | G55: H003 | H55: CarePlus Tiruppur | I55: PAT0019 | J55: Meena | K55: Female | L55: 79 | M55: Cardiology | N55: D011 | O55: Dr 11 | P55: Follow-up | Q55: Completed | R55: 74 | S55: 25 | T55: 1200 | U55: No | V55: Cash | W55: 3 | X55: No | Y55: Cardiology | Z55: =_xlfn.XLOOKUP(Appointment_Transactions[[#This Row],[Doctor_ID]],Doctor_Master[Doctor_ID],Doctor_Master[Doctor_Name],,0) -> Dr. Ramesh G
A56: APT00055 | B56: 45739 | C56: 0.625 | D56: Mar | E56: Q1 | F56: Sunday | G56: H007 | H56: CarePlus Madurai | I56: PAT0010 | J56: Hari | K56: Female | L56: 33 | M56: dermatology | N56: D006 | O56: Dr 6 | P56: Online | Q56: Completed | R56: 20 | S56: 15 | T56: 700 | U56: No | V56: UPI | W56: 3 | X56: Yes | Y56: Dermatology | Z56: =_xlfn.XLOOKUP(Appointment_Transactions[[#This Row],[Doctor_ID]],Doctor_Master[Doctor_ID],Doctor_Master[Doctor_Name],,0) -> Dr. Divya R
A57: APT00056 | B57: 45788 | C57: 0.67708333 | D57: May | E57: Q2 | F57: Sunday | G57: H005 | H57: CarePlus Erode | I57: PAT0242 | J57: Hari | K57: Male | L57: 47 | M57: Dermatology | N57: D006 | O57: Dr 6 | P57: Follow-up | Q57: Cancelled | R57: 19 | S57: 15 | T57: 700 | U57: Yes | V57: UPI | X57: Yes | Y57: Dermatology | Z57: =_xlfn.XLOOKUP(Appointment_Transactions[[#This Row],[Doctor_ID]],Doctor_Master[Doctor_ID],Doctor_Master[Doctor_Name],,0) -> Dr. Divya R
A58: APT00057 | B58: 45747 | C58: 0.6875 | D58: Mar | E58: Q1 | F58: Monday | G58: H003 | H58: CarePlus Tiruppur | I58: PAT0041 | J58: Divya | K58: Male | L58: 20 | M58: Orthopedics | N58: D002 | O58: Dr 2 | P58: Online | Q58: Completed | R58: 10 | S58: 20 | T58: 1000 | U58: No | V58: Card | W58: 4 | X58: Yes | Y58: Orthopedics | Z58: =_xlfn.XLOOKUP(Appointment_Transactions[[#This Row],[Doctor_ID]],Doctor_Master[Doctor_ID],Doctor_Master[Doctor_Name],,0) -> Dr. Priya Nair
A59: APT00058 | B59: 45750 | C59: 0.38541667 | D59: Apr | E59: Q2 | F59: Thursday | G59: H002 | H59: CarePlus Peelamedu | I59: PAT0288 | J59: Ravi | K59: Female | L59: 56 | M59: Cardiology | N59: D011 | O59: Dr 11 | P59: Online | Q59: Completed | R59: 32 | S59: 25 | T59: 1200 | U59: No | V59: Card | W59: 4 | X59: No | Y59: Cardiology | Z59: =_xlfn.XLOOKUP(Appointment_Transactions[[#This Row],[Doctor_ID]],Doctor_Master[Doctor_ID],Doctor_Master[Doctor_Name],,0) -> Dr. Ramesh G
A60: APT00059 | B60: 45710 | C60: 0.78125 | D60: Feb | E60: Q1 | F60: Saturday | G60: H005 | H60: CarePlus Erode | I60: PAT0225 | J60: Arun | K60: Male | L60: 5 | M60: ENT | N60: D018 | O60: Dr 18 | P60: Walk-in | Q60: No Show | R60: 15 | S60: 15 | T60: 650 | U60: No | V60: Cash | X60: Yes | Y60: ENT | Z60: =_xlfn.XLOOKUP(Appointment_Transactions[[#This Row],[Doctor_ID]],Doctor_Master[Doctor_ID],Doctor_Master[Doctor_Name],,0) -> Dr. Naveen C
A61: APT00060 | B61: 45693 | C61: 0.79166667 | D61: Feb | E61: Q1 | F61: Wednesday | G61: H008 | H61: CarePlus Trichy | I61: PAT0348 | J61: Divya | K61: Male | L61: 81 | M61: Ophthalmology | N61: D029 | O61: Dr 29 | P61: Follow-up | Q61: Cancelled | R61: 44 | S61: 15 | T61: 700 | U61: Yes | V61: Cash | X61: Yes | Y61: Ophthalmology | Z61: =_xlfn.XLOOKUP(Appointment_Transactions[[#This Row],[Doctor_ID]],Doctor_Master[Doctor_ID],Doctor_Master[Doctor_Name],,0) -> Dr. Manoj T
A62: APT00061 | B62: 45781 | C62: 0.36458333 | D62: May | E62: Q2 | F62: Sunday | G62: H005 | H62: CarePlus Erode | I62: PAT0162 | J62: Divya | K62: Male | L62: 58 | M62: Gynecology | N62: D037 | O62: Dr 37 | P62: Walk-in | Q62: Completed | R62: 30 | S62: 15 | T62: 900 | U62: Yes | V62: UPI | W62: 3 | X62: No | Y62: Gynecology | Z62: =_xlfn.XLOOKUP(Appointment_Transactions[[#This Row],[Doctor_ID]],Doctor_Master[Doctor_ID],Doctor_Master[Doctor_Name],,0) -> Dr. Swetha M
A63: APT00062 | B63: 45663 | C63: 0.80208333 | D63: Jan | E63: Q1 | F63: Monday | G63: H005 | H63: CarePlus Erode | I63: PAT0004 | J63: Ravi | K63: Male | L63: 9 | M63: Pediatrics | N63: D004 | O63: Dr 4 | P63: Online | Q63: No Show | R63: 19 | S63: 15 | T63: 600 | U63: No | V63: Cash | X63: No | Y63: Pediatrics | Z63: =_xlfn.XLOOKUP(Appointment_Transactions[[#This Row],[Doctor_ID]],Doctor_Master[Doctor_ID],Doctor_Master[Doctor_Name],,0) -> Dr. Meena S
A64: APT00063 | B64: 45705 | C64: 0.86458333 | D64: Feb | E64: Q1 | F64: Monday | G64: H002 | H64: CarePlus Peelamedu | I64: PAT0243 | J64: Mohan | K64: Female | L64: 38 | M64: Radiology | N64: D020 | O64: Dr 20 | P64: Walk-in | Q64: No Show | R64: 32 | S64: 15 | T64: 800 | U64: Yes | V64: Insurance | X64: No | Y64: Radiology | Z64: =_xlfn.XLOOKUP(Appointment_Transactions[[#This Row],[Doctor_ID]],Doctor_Master[Doctor_ID],Doctor_Master[Doctor_Name],,0) -> Dr. Ashwin D
A65: APT00064 | B65: 45805 | C65: 0.77083333 | D65: May | E65: Q2 | F65: Wednesday | G65: H001 | H65: CarePlus Coimbatore | I65: PAT0032 | J65: Priya | K65: Female | L65: 9 | M65: ENT | N65: D028 | O65: Dr 28 | P65: Online | Q65: Completed | R65: 22 | S65: 15 | T65: 650 | U65: No | V65: UPI | W65: 4 | X65: Yes | Y65: ENT | Z65: =_xlfn.XLOOKUP(Appointment_Transactions[[#This Row],[Doctor_ID]],Doctor_Master[Doctor_ID],Doctor_Master[Doctor_Name],,0) -> Dr. Jennifer A
A66: APT00065 | B66: 45774 | C66: 0.63541667 | D66: Apr | E66: Q2 | F66: Sunday | G66: H003 | H66: CarePlus Tiruppur | I66: PAT0328 | J66: Meena | K66: Male | L66: 24 | M66: Neurology | N66: D025 | O66: Dr 25 | P66: Follow-up | Q66: Completed | R66: 13 | S66: 30 | T66: 1300 | U66: No | V66: Cash | X66: No | Y66: Neurology | Z66: =_xlfn.XLOOKUP(Appointment_Transactions[[#This Row],[Doctor_ID]],Doctor_Master[Doctor_ID],Doctor_Master[Doctor_Name],,0) -> Dr. Bharathi K
A67: APT00066 | B67: 45731 | C67: 0.61458333 | D67: Mar | E67: Q1 | F67: Saturday | G67: H004 | H67: CarePlus Pollachi | I67: PAT0044 | J67: Kavin | K67: Female | L67: 77 | M67: Pediatrics | N67: D014 | O67: Dr 14 | P67: Walk-in | Q67: Completed | R67: 21 | S67: 15 | T67: 600 | U67: No | V67: Card | W67: 5 | X67: Yes | Y67: Pediatrics | Z67: =_xlfn.XLOOKUP(Appointment_Transactions[[#This Row],[Doctor_ID]],Doctor_Master[Doctor_ID],Doctor_Master[Doctor_Name],,0) -> Dr. Saranya S
A68: APT00067 | B68: 45792 | C68: 0.34375 | D68: May | E68: Q2 | F68: Thursday | G68: H005 | H68: CarePlus Erode | I68: PAT0052 | J68: Mohan | K68: Female | L68: 59 | M68: Cardiology | N68: D021 | O68: Dr 21 | P68: Follow-up | Q68: No Show | R68: 59 | S68: 25 | T68: 1200 | U68: No | V68: UPI | X68: No | Y68: Cardiology | Z68: =_xlfn.XLOOKUP(Appointment_Transactions[[#This Row],[Doctor_ID]],Doctor_Master[Doctor_ID],Doctor_Master[Doctor_Name],,0) -> Dr. Vignesh M
A69: APT00068 | B69: 45817 | C69: 0.73958333 | D69: Jun | E69: Q2 | F69: Monday | G69: H005 | H69: CarePlus Erode | I69: PAT0045 | J69: Arun | K69: Female | L69: 4 | M69: Ophthalmology | N69: D029 | O69: Dr 29 | P69: Walk-in | Q69: Completed | R69: 19 | S69: 15 | T69: 700 | U69: No | V69: Card | W69: 5 | X69: No | Y69: Ophthalmology | Z69: =_xlfn.XLOOKUP(Appointment_Transactions[[#This Row],[Doctor_ID]],Doctor_Master[Doctor_ID],Doctor_Master[Doctor_Name],,0) -> Dr. Manoj T
A70: APT00069 | B70: 45723 | C70: 0.85416667 | D70: Mar | E70: Q1 | F70: Friday | G70: H004 | H70: CarePlus Pollachi | I70: PAT0284 | J70: Ravi | K70: Male | L70: 54 | M70: Cardiology | N70: D021 | O70: Dr 21 | P70: Walk-in | Q70: No Show | R70: 32 | S70: 25 | T70: 1200 | U70: No | V70: UPI | X70: No | Y70: Cardiology | Z70: =_xlfn.XLOOKUP(Appointment_Transactions[[#This Row],[Doctor_ID]],Doctor_Master[Doctor_ID],Doctor_Master[Doctor_Name],,0) -> Dr. Vignesh M
A71: APT00070 | B71: 45670 | C71: 0.75 | D71: Jan | E71: Q1 | F71: Monday | G71: H007 | H71: CarePlus Madurai | I71: PAT0371 | J71: Ravi | K71: Female | L71: 34 | M71: Pediatrics | N71: D034 | O71: Dr 34 | P71: Walk-in | Q71: Completed | R71: 24 | S71: 15 | T71: 600 | U71: No | V71: UPI | W71: 3 | X71: Yes | Y71: Pediatrics | Z71: =_xlfn.XLOOKUP(Appointment_Transactions[[#This Row],[Doctor_ID]],Doctor_Master[Doctor_ID],Doctor_Master[Doctor_Name],,0) -> Dr. Abinaya K
A72: APT00071 | B72: 45768 | C72: 0.65625 | D72: Apr | E72: Q2 | F72: Monday | G72: H005 | H72: CarePlus Erode | I72: PAT0287 | J72: Hari | K72: Female | L72: 22 | M72: Neurology | N72: D035 | O72: Dr 35 | P72: Follow-up | Q72: Completed | R72: 25 | S72: 30 | T72: 1300 | U72: Yes | V72: UPI | W72: 3 | X72: No | Y72: Neurology | Z72: =_xlfn.XLOOKUP(Appointment_Transactions[[#This Row],[Doctor_ID]],Doctor_Master[Doctor_ID],Doctor_Master[Doctor_Name],,0) -> Dr. Dinesh P
A73: APT00072 | B73: 45726 | C73: 0.42708333 | D73: Mar | E73: Q1 | F73: Monday | G73: H003 | H73: CarePlus Tiruppur | I73: PAT0270 | J73: Priya | K73: Male | L73: 34 | M73: Gynecology | N73: D017 | O73: Dr 17 | P73: Online | Q73: Cancelled | R73: 33 | S73: 15 | T73: 900 | U73: No | V73: UPI | X73: Yes | Y73: Gynecology | Z73: =_xlfn.XLOOKUP(Appointment_Transactions[[#This Row],[Doctor_ID]],Doctor_Master[Doctor_ID],Doctor_Master[Doctor_Name],,0) -> Dr. Suresh B
A74: APT00073 | B74: 45714 | C74: 0.64583333 | D74: Feb | E74: Q1 | F74: Wednesday | G74: H007 | H74: CarePlus Madurai | I74: PAT0084 | J74: Nisha | K74: Male | L74: 64 | M74: Radiology | N74: D020 | O74: Dr 20 | P74: Walk-in | Q74: Completed | R74: 12 | S74: 15 | T74: 800 | U74: No | V74: Card | W74: 4 | X74: Yes | Y74: Radiology | Z74: =_xlfn.XLOOKUP(Appointment_Transactions[[#This Row],[Doctor_ID]],Doctor_Master[Doctor_ID],Doctor_Master[Doctor_Name],,0) -> Dr. Ashwin D
A75: APT00074 | B75: 45681 | C75: 0.39583333 | D75: Jan | E75: Q1 | F75: Friday | G75: H008 | H75: CarePlus Trichy | I75: PAT0158 | J75: Hari | K75: Male | L75: 27 | M75: Neurology | N75: D035 | O75: Dr 35 | P75: Follow-up | Q75: Completed | R75: 19 | S75: 30 | T75: 1300 | U75: No | V75: Cash | W75: 3 | X75: No | Y75: Neurology | Z75: =_xlfn.XLOOKUP(Appointment_Transactions[[#This Row],[Doctor_ID]],Doctor_Master[Doctor_ID],Doctor_Master[Doctor_Name],,0) -> Dr. Dinesh P
A76: APT00075 | B76: 45778 | C76: 0.71875 | D76: May | E76: Q2 | F76: Thursday | G76: H003 | H76: CarePlus Tiruppur | I76: PAT0227 | J76: Ravi | K76: Female | L76: 52 | M76: Neurology | N76: D035 | O76: Dr 35 | P76: Walk-in | Q76: No Show | R76: 12 | S76: 30 | T76: 1300 | U76: No | V76: UPI | X76: Yes | Y76: Neurology | Z76: =_xlfn.XLOOKUP(Appointment_Transactions[[#This Row],[Doctor_ID]],Doctor_Master[Doctor_ID],Doctor_Master[Doctor_Name],,0) -> Dr. Dinesh P
A77: APT00076 | B77: 45709 | C77: 0.80208333 | D77: Feb | E77: Q1 | F77: Friday | G77: H007 | H77: CarePlus Madurai | I77: PAT0130 | J77: Mohan | K77: Female | L77: 6 | M77: ENT | N77: D008 | O77: Dr 8 | P77: Online | Q77: Completed | R77: 11 | S77: 15 | T77: 650 | U77: Yes | V77: Insurance | W77: 3 | X77: No | Y77: ENT | Z77: =_xlfn.XLOOKUP(Appointment_Transactions[[#This Row],[Doctor_ID]],Doctor_Master[Doctor_ID],Doctor_Master[Doctor_Name],,0) -> Dr. Lakshmi K
A78: APT00077 | B78: 45757 | C78: 0.83333333 | D78: Apr | E78: Q2 | F78: Thursday | G78: H006 | H78: CarePlus Salem | I78: PAT0157 | J78: Hari | K78: Female | L78: 45 | M78: Ophthalmology | N78: D029 | O78: Dr 29 | P78: Online | Q78: Completed | R78: 22 | S78: 15 | T78: 700 | U78: No | V78: UPI | W78: 5 | X78: Yes | Y78: Ophthalmology | Z78: =_xlfn.XLOOKUP(Appointment_Transactions[[#This Row],[Doctor_ID]],Doctor_Master[Doctor_ID],Doctor_Master[Doctor_Name],,0) -> Dr. Manoj T
A79: APT00078 | B79: 45710 | C79: 0.60416667 | D79: Feb | E79: Q1 | F79: Saturday | G79: H007 | H79: CarePlus Madurai | I79: PAT0201 | J79: Meena | K79: Female | L79: 45 | M79: Orthopedics | N79: D022 | O79: Dr 22 | P79: Walk-in | Q79: Completed | R79: 10 | S79: 20 | T79: 1000 | U79: No | V79: UPI | X79: Yes | Y79: Orthopedics | Z79: =_xlfn.XLOOKUP(Appointment_Transactions[[#This Row],[Doctor_ID]],Doctor_Master[Doctor_ID],Doctor_Master[Doctor_Name],,0) -> Dr. Ramya P
A80: APT00079 | B80: 45817 | C80: 0.5625 | D80: Jun | E80: Q2 | F80: Monday | G80: H002 | H80: CarePlus Peelamedu | I80: PAT0210 | J80: Arun | K80: Female | L80: 73 | M80: General Medicine | N80: D003 | O80: Dr 3 | P80: Online | Q80: Cancelled | R80: 11 | S80: 15 | T80: 500 | U80: No | V80: UPI | X80: No | Y80: General Medicine | Z80: =_xlfn.XLOOKUP(Appointment_Transactions[[#This Row],[Doctor_ID]],Doctor_Master[Doctor_ID],Doctor_Master[Doctor_Name],,0) -> Dr. Karthik Raj
A81: APT00080 | B81: 45821 | C81: 0.51041667 | D81: Jun | E81: Q2 | F81: Friday | G81: H008 | H81: CarePlus Trichy | I81: PAT0079 | J81: Kavin | K81: Male | L81: 80 | M81: Pediatrics | N81: D004 | O81: Dr 4 | P81: Follow-up | Q81: Cancelled | R81: 35 | S81: 15 | T81: 600 | U81: Yes | V81: Cash | X81: Yes | Y81: Pediatrics | Z81: =_xlfn.XLOOKUP(Appointment_Transactions[[#This Row],[Doctor_ID]],Doctor_Master[Doctor_ID],Doctor_Master[Doctor_Name],,0) -> Dr. Meena S
A82: APT00081 | B82: 45782 | C82: 0.51041667 | D82: May | E82: Q2 | F82: Monday | G82: H004 | H82: CarePlus Pollachi | I82: PAT0078 | J82: Priya | K82: Male | L82: 83 | M82: Ophthalmology | N82: D039 | O82: Dr 39 | P82: Follow-up | Q82: Completed | R82: 36 | S82: 15 | T82: 700 | U82: Yes | V82: UPI | W82: 4 | X82: No | Y82: Ophthalmology | Z82: =_xlfn.XLOOKUP(Appointment_Transactions[[#This Row],[Doctor_ID]],Doctor_Master[Doctor_ID],Doctor_Master[Doctor_Name],,0) -> Dr. Ranjani S
A83: APT00082 | B83: 45746 | C83: 0.39583333 | D83: Mar | E83: Q1 | F83: Sunday | G83: H002 | H83: CarePlus Peelamedu | I83: PAT0349 | J83: Kavin | K83: Male | L83: 17 | M83: Radiology | N83: D040 | O83: Dr 40 | P83: Online | Q83: No Show | R83: 18 | S83: 15 | T83: 800 | U83: No | V83: UPI | X83: No | Y83: Radiology | Z83: =_xlfn.XLOOKUP(Appointment_Transactions[[#This Row],[Doctor_ID]],Doctor_Master[Doctor_ID],Doctor_Master[Doctor_Name],,0) -> Dr. Balaji V
A84: APT00083 | B84: 45713 | C84: 0.51041667 | D84: Feb | E84: Q1 | F84: Tuesday | G84: H004 | H84: CarePlus Pollachi | I84: PAT0237 | J84: Ravi | K84: Male | L84: 69 | M84: Neurology | N84: D025 | O84: Dr 25 | P84: Online | Q84: Completed | R84: 22 | S84: 30 | T84: 1300 | U84: Yes | V84: UPI | W84: 3 | X84: Yes | Y84: Neurology | Z84: =_xlfn.XLOOKUP(Appointment_Transactions[[#This Row],[Doctor_ID]],Doctor_Master[Doctor_ID],Doctor_Master[Doctor_Name],,0) -> Dr. Bharathi K
A85: APT00084 | B85: 45745 | C85: 0.5 | D85: Mar | E85: Q1 | F85: Saturday | G85: H001 | H85: CarePlus Coimbatore | I85: PAT0059 | J85: Arun | K85: Male | L85: 21 | M85: Pediatrics | N85: D014 | O85: Dr 14 | P85: Online | Q85: Completed | R85: 32 | S85: 15 | T85: 600 | U85: No | V85: UPI | W85: 4 | X85: Yes | Y85: Pediatrics | Z85: =_xlfn.XLOOKUP(Appointment_Transactions[[#This Row],[Doctor_ID]],Doctor_Master[Doctor_ID],Doctor_Master[Doctor_Name],,0) -> Dr. Saranya S
A86: APT00085 | B86: 45674 | C86: 0.75 | D86: Jan | E86: Q1 | F86: Friday | G86: H001 | H86: CarePlus Coimbatore | I86: PAT0206 | J86: Divya | K86: Male | L86: 52 | M86: Pediatrics | N86: D034 | O86: Dr 34 | P86: Follow-up | Q86: Completed | R86: 35 | S86: 15 | T86: 600 | U86: No | V86: Cash | W86: 4 | X86: No | Y86: Pediatrics | Z86: =_xlfn.XLOOKUP(Appointment_Transactions[[#This Row],[Doctor_ID]],Doctor_Master[Doctor_ID],Doctor_Master[Doctor_Name],,0) -> Dr. Abinaya K
A87: APT00086 | B87: 45735 | C87: 0.78125 | D87: Mar | E87: Q1 | F87: Wednesday | G87: H005 | H87: CarePlus Erode | I87: PAT0062 | J87: Hari | K87: Female | L87: 22 | M87: General Medicine | N87: D013 | O87: Dr 13 | P87: Follow-up | Q87: Cancelled | R87: 18 | S87: 15 | T87: 500 | U87: No | V87: UPI | X87: No | Y87: General Medicine | Z87: =_xlfn.XLOOKUP(Appointment_Transactions[[#This Row],[Doctor_ID]],Doctor_Master[Doctor_ID],Doctor_Master[Doctor_Name],,0) -> Dr. Prakash R
A88: APT00087 | B88: 45710 | C88: 0.41666667 | D88: Feb | E88: Q1 | F88: Saturday | G88: H007 | H88: CarePlus Madurai | I88: PAT0239 | J88: Lakshmi | K88: Male | L88: 59 | M88: ENT | N88: D028 | O88: Dr 28 | P88: Follow-up | Q88: Completed | R88: 31 | S88: 15 | T88: 650 | U88: No | V88: Card | W88: 5 | X88: No | Y88: ENT | Z88: =_xlfn.XLOOKUP(Appointment_Transactions[[#This Row],[Doctor_ID]],Doctor_Master[Doctor_ID],Doctor_Master[Doctor_Name],,0) -> Dr. Jennifer A
A89: APT00088 | B89: 45661 | C89: 0.73958333 | D89: Jan | E89: Q1 | F89: Saturday | G89: H008 | H89: CarePlus Trichy | I89: PAT0324 | J89: Lakshmi | K89: Female | L89: 81 | M89: Pediatrics | N89: D034 | O89: Dr 34 | P89: Walk-in | Q89: Completed | R89: 5 | S89: 15 | T89: 600 | U89: No | V89: UPI | W89: 4 | X89: Yes | Y89: Pediatrics | Z89: =_xlfn.XLOOKUP(Appointment_Transactions[[#This Row],[Doctor_ID]],Doctor_Master[Doctor_ID],Doctor_Master[Doctor_Name],,0) -> Dr. Abinaya K
A90: APT00089 | B90: 45722 | C90: 0.72916667 | D90: Mar | E90: Q1 | F90: Thursday | G90: H004 | H90: CarePlus Pollachi | I90: PAT0109 | J90: Ravi | K90: Female | L90: 71 | M90: Cardiology | N90: D011 | O90: Dr 11 | P90: Online | Q90: Completed | R90: 56 | S90: 25 | T90: 1200 | U90: No | V90: UPI | W90: 3 | X90: Yes | Y90: Cardiology | Z90: =_xlfn.XLOOKUP(Appointment_Transactions[[#This Row],[Doctor_ID]],Doctor_Master[Doctor_ID],Doctor_Master[Doctor_Name],,0) -> Dr. Ramesh G
A91: APT00090 | B91: 45760 | C91: 0.375 | D91: Apr | E91: Q2 | F91: Sunday | G91: H004 | H91: CarePlus Pollachi | I91: PAT0268 | J91: Lakshmi | K91: Female | L91: 85 | M91: ENT | N91: D038 | O91: Dr 38 | P91: Follow-up | Q91: Cancelled | R91: 13 | S91: 15 | T91: 650 | U91: No | V91: UPI | X91: No | Y91: ENT | Z91: =_xlfn.XLOOKUP(Appointment_Transactions[[#This Row],[Doctor_ID]],Doctor_Master[Doctor_ID],Doctor_Master[Doctor_Name],,0) -> Dr. Ajith K
A92: APT00091 | B92: 45759 | C92: 0.5625 | D92: Apr | E92: Q2 | F92: Saturday | G92: H006 | H92: CarePlus Salem | I92: PAT0036 | J92: Mohan | K92: Male | L92: 46 | M92: Neurology | N92: D015 | O92: Dr 15 | P92: Online | Q92: Cancelled | R92: 32 | S92: 30 | T92: 1300 | U92: No | V92: UPI | X92: No | Y92: Neurology | Z92: =_xlfn.XLOOKUP(Appointment_Transactions[[#This Row],[Doctor_ID]],Doctor_Master[Doctor_ID],Doctor_Master[Doctor_Name],,0) -> Dr. Vinoth K
A93: APT00092 | B93: 45672 | C93: 0.65625 | D93: Jan | E93: Q1 | F93: Wednesday | G93: H008 | H93: CarePlus Trichy | I93: PAT0264 | J93: Meena | K93: Male | L93: 62 | M93: Cardiology | N93: D031 | O93: Dr 31 | P93: Online | Q93: Cancelled | R93: 26 | S93: 25 | T93: 1200 | U93: Yes | V93: Insurance | X93: Yes | Y93: Cardiology | Z93: =_xlfn.XLOOKUP(Appointment_Transactions[[#This Row],[Doctor_ID]],Doctor_Master[Doctor_ID],Doctor_Master[Doctor_Name],,0) -> Dr. Senthil M
A94: APT00093 | B94: 45786 | C94: 0.34375 | D94: May | E94: Q2 | F94: Friday | G94: H002 | H94: CarePlus Peelamedu | I94: PAT0105 | J94: Ravi | K94: Male | L94: 20 | M94: Radiology | N94: D020 | O94: Dr 20 | P94: Walk-in | Q94: Completed | R94: 19 | S94: 15 | T94: 800 | U94: Yes | V94: Card | W94: 4 | X94: Yes | Y94: Radiology | Z94: =_xlfn.XLOOKUP(Appointment_Transactions[[#This Row],[Doctor_ID]],Doctor_Master[Doctor_ID],Doctor_Master[Doctor_Name],,0) -> Dr. Ashwin D
A95: APT00094 | B95: 45739 | C95: 0.58333333 | D95: Mar | E95: Q1 | F95: Sunday | G95: H003 | H95: CarePlus Tiruppur | I95: PAT0132 | J95: Meena | K95: Male | L95: 10 | M95: ENT | N95: D018 | O95: Dr 18 | P95: Follow-up | Q95: Completed | R95: 10 | S95: 15 | T95: 650 | U95: No | V95: UPI | X95: No | Y95: ENT | Z95: =_xlfn.XLOOKUP(Appointment_Transactions[[#This Row],[Doctor_ID]],Doctor_Master[Doctor_ID],Doctor_Master[Doctor_Name],,0) -> Dr. Naveen C
A96: APT00095 | B96: 45773 | C96: 0.4375 | D96: Apr | E96: Q2 | F96: Saturday | G96: H008 | H96: CarePlus Trichy | I96: PAT0308 | J96: Mohan | K96: Female | L96: 43 | M96: Cardiology | N96: D021 | O96: Dr 21 | P96: Follow-up | Q96: No Show | R96: 52 | S96: 25 | T96: 1200 | U96: No | V96: UPI | X96: No | Y96: Cardiology | Z96: =_xlfn.XLOOKUP(Appointment_Transactions[[#This Row],[Doctor_ID]],Doctor_Master[Doctor_ID],Doctor_Master[Doctor_Name],,0) -> Dr. Vignesh M
A97: APT00096 | B97: 45764 | C97: 0.34375 | D97: Apr | E97: Q2 | F97: Thursday | G97: H001 | H97: CarePlus Coimbatore | I97: PAT0280 | J97: Mohan | K97: Male | L97: 71 | M97: Neurology | N97: D015 | O97: Dr 15 | P97: Walk-in | Q97: Completed | R97: 40 | S97: 30 | T97: 1300 | U97: Yes | V97: Card | W97: 3 | X97: No | Y97: Neurology | Z97: =_xlfn.XLOOKUP(Appointment_Transactions[[#This Row],[Doctor_ID]],Doctor_Master[Doctor_ID],Doctor_Master[Doctor_Name],,0) -> Dr. Vinoth K
A98: APT00097 | B98: 45735 | C98: 0.48958333 | D98: Mar | E98: Q1 | F98: Wednesday | G98: H001 | H98: CarePlus Coimbatore | I98: PAT0209 | J98: Kavin | K98: Female | L98: 75 | M98: Pediatrics | N98: D004 | O98: Dr 4 | P98: Walk-in | Q98: Completed | R98: 17 | S98: 15 | T98: 600 | U98: Yes | V98: UPI | W98: 4 | X98: Yes | Y98: Pediatrics | Z98: =_xlfn.XLOOKUP(Appointment_Transactions[[#This Row],[Doctor_ID]],Doctor_Master[Doctor_ID],Doctor_Master[Doctor_Name],,0) -> Dr. Meena S
A99: APT00098 | B99: 45814 | C99: 0.48958333 | D99: Jun | E99: Q2 | F99: Friday | G99: H001 | H99: CarePlus Coimbatore | I99: PAT0028 | J99: Hari | K99: Male | L99: 58 | M99: Radiology | N99: D040 | O99: Dr 40 | P99: Online | Q99: Cancelled | R99: 30 | S99: 15 | T99: 800 | U99: No | V99: UPI | X99: No | Y99: Radiology | Z99: =_xlfn.XLOOKUP(Appointment_Transactions[[#This Row],[Doctor_ID]],Doctor_Master[Doctor_ID],Doctor_Master[Doctor_Name],,0) -> Dr. Balaji V
A100: APT00099 | B100: 45757 | C100: 0.79166667 | D100: Apr | E100: Q2 | F100: Thursday | G100: H003 | H100: CarePlus Tiruppur | I100: PAT0114 | J100: Priya | K100: Female | L100: 4 | M100: Radiology | N100: D040 | O100: Dr 40 | P100: Online | Q100: Cancelled | R100: 31 | S100: 15 | T100: 800 | U100: Yes | V100: Card | X100: No | Y100: Radiology | Z100: =_xlfn.XLOOKUP(Appointment_Transactions[[#This Row],[Doctor_ID]],Doctor_Master[Doctor_ID],Doctor_Master[Doctor_Name],,0) -> Dr. Balaji V
...
